ctextcore/__init__.py
ctextcore/_version.py
ctextcore/core.py
ctextcore/requirements.txt
ctextcore/core/CTexTCore-2.0.jar
ctextcore/server/__init__.py
ctextcore/server/_version.py
ctextcore/server/client.py
ctextcore/server/utils.py
ctextcore/tests/__init__.py
ctextcore/tests/test_lemma.py
ctextcore/tests/test_morph.py
ctextcore/tests/test_ner.py
ctextcore/tests/test_ocr.py
ctextcore/tests/test_pc.py
ctextcore/tests/test_pos.py
ctextcore/tests/test_sent.py
ctextcore/tests/test_tok.py
ctextcore/tests/test_update.py
ctextcore/tests/test_upos.py
ctextcore/tests/test_zalid.py
ctextcore/tests/data/installed_versions_updates.json
ctextcore/tests/data/expected/file_level/lemma/af.lemma.output.expected.delimited.txt
ctextcore/tests/data/expected/file_level/lemma/af.lemma.output.expected.json.json
ctextcore/tests/data/expected/file_level/lemma/af.lemma.output.expected.list.txt
ctextcore/tests/data/expected/file_level/lemma/nr.lemma.output.expected.delimited.txt
ctextcore/tests/data/expected/file_level/lemma/nr.lemma.output.expected.json.json
ctextcore/tests/data/expected/file_level/lemma/nr.lemma.output.expected.list.txt
ctextcore/tests/data/expected/file_level/lemma/nso.lemma.output.expected.delimited.txt
ctextcore/tests/data/expected/file_level/lemma/nso.lemma.output.expected.json.json
ctextcore/tests/data/expected/file_level/lemma/nso.lemma.output.expected.list.txt
ctextcore/tests/data/expected/file_level/lemma/ss.lemma.output.expected.delimited.txt
ctextcore/tests/data/expected/file_level/lemma/ss.lemma.output.expected.json.json
ctextcore/tests/data/expected/file_level/lemma/ss.lemma.output.expected.list.txt
ctextcore/tests/data/expected/file_level/lemma/st.lemma.output.expected.delimited.txt
ctextcore/tests/data/expected/file_level/lemma/st.lemma.output.expected.json.json
ctextcore/tests/data/expected/file_level/lemma/st.lemma.output.expected.list.txt
ctextcore/tests/data/expected/file_level/lemma/tn.lemma.output.expected.delimited.txt
ctextcore-1.0.0.dist-info/LICENSE.txt
ctextcore-1.0.0.dist-info/METADATA
ctextcore-1.0.0.dist-info/WHEEL
ctextcore-1.0.0.dist-info/top_level.txt
ctextcore-1.0.0.dist-info/RECORD
