Metadata-Version: 2.2
Name: ctextcore
Version: 1.0.0
Summary: An open-source Python package for existing NCHLT core technologies for ten South African languages.
Author-email: "Centre for Text Technology (CTexT)" <ctextdev@gmail.com>
License: Apache License 2.0
Keywords: nchlt,ctextcore,CTexT,nlp,South African languages,Afrikaans,isiNdebele,isiXhosa,isiZulu,Setswana,Sepedi,Sesotho,Siswati,Tshivenḓa,Xitsonga
Classifier: Programming Language :: Python :: 3.8
Classifier: Programming Language :: Python :: 3.9
Classifier: Programming Language :: Python :: 3.10
Classifier: Programming Language :: Python :: 3.11
Classifier: Programming Language :: Python :: 3.12
Classifier: Programming Language :: Java
Classifier: Operating System :: OS Independent
Requires-Python: >=3.8
License-File: LICENSE.txt
Requires-Dist: requests~=2.32
